[{"name":"305131.衡阳大众健康民欣药房有限公司 (湘DA7341208（更）)","url":"javascript:commitForECMA(callbackC,'content.jsp?tableId=41&tableName=TABLE41&tableView=%E8%8D%AF%E5%93%81%E7%BB%8F%E8%90%A5%E4%BC%81%E4%B8%9A&Id=285734',null)"},{"name":"305132.长沙市天心区暮云街道福园养天和大药房 (湘CB7310966)","url":"javascript:commitForECMA(callbackC,'content.jsp?tableId=41&tableName=TABLE41&tableView=%E8%8D%AF%E5%93%81%E7%BB%8F%E8%90%A5%E4%BC%81%E4%B8%9A&Id=285735',null)"},{"name":"305133.无锡市桃源大药房有限公司 (苏DA5105039)","url":"javascript:commitForECMA(callbackC,'content.jsp?tableId=41&tableName=TABLE41&tableView=%E8%8D%AF%E5%93%81%E7%BB%8F%E8%90%A5%E4%BC%81%E4%B8%9A&Id=285736',null)"},{"name":"305134.惠安县得安堂医药连锁有限公司厦门仙岳路店 (闽CB5921139)","url":"javascript:commitForECMA(callbackC,'content.jsp?tableId=41&tableName=TABLE41&tableView=%E8%8D%AF%E5%93%81%E7%BB%8F%E8%90%A5%E4%BC%81%E4%B8%9A&Id=285737',null)"},{"name":"305135.湖南康尔佳宝庆大药房连锁有限公司绥宁瓦屋药店 (湘CA7395047)","url":"javascript:commitForECMA(callbackC,'content.jsp?tableId=41&tableName=TABLE41&tableView=%E8%8D%AF%E5%93%81%E7%BB%8F%E8%90%A5%E4%BC%81%E4%B8%9A&Id=285738',null)"},{"name":"305136.山东立健药店连锁有限公司莱州紫景花园店 (鲁CB5354591)","url":"javascript:commitForECMA(callbackC,'content.jsp?tableId=41&tableName=TABLE41&tableView=%E8%8D%AF%E5%93%81%E7%BB%8F%E8%90%A5%E4%BC%81%E4%B8%9A&Id=285739',null)"},{"name":"305137.永州市冷水滩区中南新农村大药房银象路店 (湘CB746S013（换）)","url":"javascript:commitForECMA(callbackC,'content.jsp?tableId=41&tableName=TABLE41&tableView=%E8%8D%AF%E5%93%81%E7%BB%8F%E8%90%A5%E4%BC%81%E4%B8%9A&Id=285740',null)"},{"name":"305138.新化县时珍大药房麻屋冲店 (湘DB07385018)","url":"javascript:commitForECMA(callbackC,'content.jsp?tableId=41&tableName=TABLE41&tableView=%E8%8D%AF%E5%93%81%E7%BB%8F%E8%90%A5%E4%BC%81%E4%B8%9A&Id=285741',null)"},{"name":"305139.岳阳市岳阳楼区太汲神药房 (湘DA730076(2015LQ))","url":"javascript:commitForECMA(callbackC,'content.jsp?tableId=41&tableName=TABLE41&tableView=%E8%8D%AF%E5%93%81%E7%BB%8F%E8%90%A5%E4%BC%81%E4%B8%9A&Id=285742',null)"},{"name":"305140.余庆县大乌江镇益康大药房 (黔DB520328165)","url":"javascript:commitForECMA(callbackC,'content.jsp?tableId=41&tableName=TABLE41&tableView=%E8%8D%AF%E5%93%81%E7%BB%8F%E8%90%A5%E4%BC%81%E4%B8%9A&Id=285743',null)"},{"name":"305141.余庆县大乌江镇新场村安康药房 (黔DB520328164)","url":"javascript:commitForECMA(callbackC,'content.jsp?tableId=41&tableName=TABLE41&tableView=%E8%8D%AF%E5%93%81%E7%BB%8F%E8%90%A5%E4%BC%81%E4%B8%9A&Id=285744',null)"},{"name":"305142.邹城市天惠阳光医药连锁有限公司亲民药店 (鲁CB5370815)","url":"javascript:commitForECMA(callbackC,'content.jsp?tableId=41&tableName=TABLE41&tableView=%E8%8D%AF%E5%93%81%E7%BB%8F%E8%90%A5%E4%BC%81%E4%B8%9A&Id=285745',null)"},{"name":"305143.贵州省四季康药业连锁有限公司余庆九十三分店 (黔DB520328163)","url":"javascript:commitForECMA(callbackC,'content.jsp?tableId=41&tableName=TABLE41&tableView=%E8%8D%AF%E5%93%81%E7%BB%8F%E8%90%A5%E4%BC%81%E4%B8%9A&Id=285746',null)"},{"name":"305144.天津市旭升大药房有限公司 (津DA2210022)","url":"javascript:commitForECMA(callbackC,'content.jsp?tableId=41&tableName=TABLE41&tableView=%E8%8D%AF%E5%93%81%E7%BB%8F%E8%90%A5%E4%BC%81%E4%B8%9A&Id=285747',null)"},{"name":"305145.天津市同善堂药店有限公司 (津DA2210024)","url":"javascript:commitForECMA(callbackC,'content.jsp?tableId=41&tableName=TABLE41&tableView=%E8%8D%AF%E5%93%81%E7%BB%8F%E8%90%A5%E4%BC%81%E4%B8%9A&Id=285748',null)"}]