[{"name":"355231.新津县民森大药房（四川康贝大药房连锁有限公司） (川CA0288964)","url":"javascript:commitForECMA(callbackC,'content.jsp?tableId=41&tableName=TABLE41&tableView=%E8%8D%AF%E5%93%81%E7%BB%8F%E8%90%A5%E4%BC%81%E4%B8%9A&Id=353678',null)"},{"name":"355232.北京高远百康大药房有限公司霁月园分店 (京CB0916001)","url":"javascript:commitForECMA(callbackC,'content.jsp?tableId=41&tableName=TABLE41&tableView=%E8%8D%AF%E5%93%81%E7%BB%8F%E8%90%A5%E4%BC%81%E4%B8%9A&Id=353679',null)"},{"name":"355233.张家口佰汇大药房连锁有限公司怀安县东辰路店 (冀CB31306091)","url":"javascript:commitForECMA(callbackC,'content.jsp?tableId=41&tableName=TABLE41&tableView=%E8%8D%AF%E5%93%81%E7%BB%8F%E8%90%A5%E4%BC%81%E4%B8%9A&Id=353680',null)"},{"name":"355234.北京梓林堂大药房有限公司 (京DA2216018)","url":"javascript:commitForECMA(callbackC,'content.jsp?tableId=41&tableName=TABLE41&tableView=%E8%8D%AF%E5%93%81%E7%BB%8F%E8%90%A5%E4%BC%81%E4%B8%9A&Id=353681',null)"},{"name":"355235.麦克红康药房奉节县三台店 (渝CB0340298)","url":"javascript:commitForECMA(callbackC,'content.jsp?tableId=41&tableName=TABLE41&tableView=%E8%8D%AF%E5%93%81%E7%BB%8F%E8%90%A5%E4%BC%81%E4%B8%9A&Id=354011',null)"},{"name":"355236.江岸大药房重庆市南川区文凤明川药店 (渝CA1808255)","url":"javascript:commitForECMA(callbackC,'content.jsp?tableId=41&tableName=TABLE41&tableView=%E8%8D%AF%E5%93%81%E7%BB%8F%E8%90%A5%E4%BC%81%E4%B8%9A&Id=354012',null)"},{"name":"355237.重庆衡生医药连锁有限责任公司衡生大药房南川区南大街连锁店店 (渝CB0180287)","url":"javascript:commitForECMA(callbackC,'content.jsp?tableId=41&tableName=TABLE41&tableView=%E8%8D%AF%E5%93%81%E7%BB%8F%E8%90%A5%E4%BC%81%E4%B8%9A&Id=354013',null)"},{"name":"355238.南川区巨意药房 (渝DA0180271)","url":"javascript:commitForECMA(callbackC,'content.jsp?tableId=41&tableName=TABLE41&tableView=%E8%8D%AF%E5%93%81%E7%BB%8F%E8%90%A5%E4%BC%81%E4%B8%9A&Id=354014',null)"},{"name":"355239.南川区永安药房 (渝DA0180266)","url":"javascript:commitForECMA(callbackC,'content.jsp?tableId=41&tableName=TABLE41&tableView=%E8%8D%AF%E5%93%81%E7%BB%8F%E8%90%A5%E4%BC%81%E4%B8%9A&Id=354015',null)"},{"name":"355240.南川区福渝堂药房御锦江山店 (渝DA0180240)","url":"javascript:commitForECMA(callbackC,'content.jsp?tableId=41&tableName=TABLE41&tableView=%E8%8D%AF%E5%93%81%E7%BB%8F%E8%90%A5%E4%BC%81%E4%B8%9A&Id=354016',null)"},{"name":"355241.南川区廖盛利大药房 (渝DA0180222)","url":"javascript:commitForECMA(callbackC,'content.jsp?tableId=41&tableName=TABLE41&tableView=%E8%8D%AF%E5%93%81%E7%BB%8F%E8%90%A5%E4%BC%81%E4%B8%9A&Id=354017',null)"},{"name":"355242.南川区莲蓉药房福寿药店 (渝DA0180218)","url":"javascript:commitForECMA(callbackC,'content.jsp?tableId=41&tableName=TABLE41&tableView=%E8%8D%AF%E5%93%81%E7%BB%8F%E8%90%A5%E4%BC%81%E4%B8%9A&Id=354018',null)"},{"name":"355243.重庆桐君阁大药房连锁有限责任公司保康参茸店 (渝CA0040073)","url":"javascript:commitForECMA(callbackC,'content.jsp?tableId=41&tableName=TABLE41&tableView=%E8%8D%AF%E5%93%81%E7%BB%8F%E8%90%A5%E4%BC%81%E4%B8%9A&Id=354019',null)"},{"name":"355244.明星大药房重庆市渝中区直人堂药店 (渝CB0040077)","url":"javascript:commitForECMA(callbackC,'content.jsp?tableId=41&tableName=TABLE41&tableView=%E8%8D%AF%E5%93%81%E7%BB%8F%E8%90%A5%E4%BC%81%E4%B8%9A&Id=354020',null)"},{"name":"355245.万鑫药房重庆市渝中区平高堂药房 (渝CB0040058)","url":"javascript:commitForECMA(callbackC,'content.jsp?tableId=41&tableName=TABLE41&tableView=%E8%8D%AF%E5%93%81%E7%BB%8F%E8%90%A5%E4%BC%81%E4%B8%9A&Id=354021',null)"}]