[{"name":"397351.成华区立康大药房 (川DA0280474(13))","url":"javascript:commitForECMA(callbackC,'content.jsp?tableId=41&tableName=TABLE41&tableView=%E8%8D%AF%E5%93%81%E7%BB%8F%E8%90%A5%E4%BC%81%E4%B8%9A&Id=393438',null)"},{"name":"397352.开封市祥符区医药总公司兴隆医药零售店 (豫DA3780604)","url":"javascript:commitForECMA(callbackC,'content.jsp?tableId=41&tableName=TABLE41&tableView=%E8%8D%AF%E5%93%81%E7%BB%8F%E8%90%A5%E4%BC%81%E4%B8%9A&Id=393439',null)"},{"name":"397353.眉山市东坡区宏欣药堂 (川DB2100066)","url":"javascript:commitForECMA(callbackC,'content.jsp?tableId=41&tableName=TABLE41&tableView=%E8%8D%AF%E5%93%81%E7%BB%8F%E8%90%A5%E4%BC%81%E4%B8%9A&Id=393440',null)"},{"name":"397354.武陟县永济药品零售连锁有限责任公司保安堂大药房 (豫CB3910509)","url":"javascript:commitForECMA(callbackC,'content.jsp?tableId=41&tableName=TABLE41&tableView=%E8%8D%AF%E5%93%81%E7%BB%8F%E8%90%A5%E4%BC%81%E4%B8%9A&Id=393441',null)"},{"name":"397355.温江涌泉同聚堂大药房 (川DA0280485(13))","url":"javascript:commitForECMA(callbackC,'content.jsp?tableId=41&tableName=TABLE41&tableView=%E8%8D%AF%E5%93%81%E7%BB%8F%E8%90%A5%E4%BC%81%E4%B8%9A&Id=393442',null)"},{"name":"397356.安阳市益心堂大药房有限公司东区八中店 (豫DB3720876)","url":"javascript:commitForECMA(callbackC,'content.jsp?tableId=41&tableName=TABLE41&tableView=%E8%8D%AF%E5%93%81%E7%BB%8F%E8%90%A5%E4%BC%81%E4%B8%9A&Id=393443',null)"},{"name":"397357.汉源县冯启林零售药店 (川DB8350028)","url":"javascript:commitForECMA(callbackC,'content.jsp?tableId=41&tableName=TABLE41&tableView=%E8%8D%AF%E5%93%81%E7%BB%8F%E8%90%A5%E4%BC%81%E4%B8%9A&Id=393421',null)"},{"name":"397358.海南德祥堂药品经营连锁超市有限公司佳品分店 (琼CB 0200078Ⅲ)","url":"javascript:commitForECMA(callbackC,'content.jsp?tableId=41&tableName=TABLE41&tableView=%E8%8D%AF%E5%93%81%E7%BB%8F%E8%90%A5%E4%BC%81%E4%B8%9A&Id=393785',null)"},{"name":"397359.海南三叶大药房连锁经营有限公司三亚荔枝沟分店 (琼CB 0200075Ⅲ)","url":"javascript:commitForECMA(callbackC,'content.jsp?tableId=41&tableName=TABLE41&tableView=%E8%8D%AF%E5%93%81%E7%BB%8F%E8%90%A5%E4%BC%81%E4%B8%9A&Id=393786',null)"},{"name":"397360.兴文县老百姓大药房 (川DB8311583)","url":"javascript:commitForECMA(callbackC,'content.jsp?tableId=41&tableName=TABLE41&tableView=%E8%8D%AF%E5%93%81%E7%BB%8F%E8%90%A5%E4%BC%81%E4%B8%9A&Id=393787',null)"},{"name":"397361.汉源县李氏药店 (川DB8350029)","url":"javascript:commitForECMA(callbackC,'content.jsp?tableId=41&tableName=TABLE41&tableView=%E8%8D%AF%E5%93%81%E7%BB%8F%E8%90%A5%E4%BC%81%E4%B8%9A&Id=393788',null)"},{"name":"397362.雅安市雨城区养生堂药店 (川DB8350031)","url":"javascript:commitForECMA(callbackC,'content.jsp?tableId=41&tableName=TABLE41&tableView=%E8%8D%AF%E5%93%81%E7%BB%8F%E8%90%A5%E4%BC%81%E4%B8%9A&Id=393789',null)"},{"name":"397363.雅安市雨城区怡仁堂大药房 (川DB8350032)","url":"javascript:commitForECMA(callbackC,'content.jsp?tableId=41&tableName=TABLE41&tableView=%E8%8D%AF%E5%93%81%E7%BB%8F%E8%90%A5%E4%BC%81%E4%B8%9A&Id=393790',null)"},{"name":"397364.西华县医药公司同济堂大药房 (豫DA3942079)","url":"javascript:commitForECMA(callbackC,'content.jsp?tableId=41&tableName=TABLE41&tableView=%E8%8D%AF%E5%93%81%E7%BB%8F%E8%90%A5%E4%BC%81%E4%B8%9A&Id=393791',null)"},{"name":"397365.海南德祥堂药品经营连锁超市有限公司新风路分店 (琼CB 0200079Ⅲ)","url":"javascript:commitForECMA(callbackC,'content.jsp?tableId=41&tableName=TABLE41&tableView=%E8%8D%AF%E5%93%81%E7%BB%8F%E8%90%A5%E4%BC%81%E4%B8%9A&Id=393792',null)"}]