[{"name":"403951.重庆市涪陵区修正堂学府药店 (渝CA0020403)","url":"javascript:commitForECMA(callbackC,'content.jsp?tableId=41&tableName=TABLE41&tableView=%E8%8D%AF%E5%93%81%E7%BB%8F%E8%90%A5%E4%BC%81%E4%B8%9A&Id=400781',null)"},{"name":"403952.铁岭县新台子镇维康药店 (辽DB4104136)","url":"javascript:commitForECMA(callbackC,'content.jsp?tableId=41&tableName=TABLE41&tableView=%E8%8D%AF%E5%93%81%E7%BB%8F%E8%90%A5%E4%BC%81%E4%B8%9A&Id=400782',null)"},{"name":"403953.通海县杨广宝芝灵药店 (滇Da0423004)","url":"javascript:commitForECMA(callbackC,'content.jsp?tableId=41&tableName=TABLE41&tableView=%E8%8D%AF%E5%93%81%E7%BB%8F%E8%90%A5%E4%BC%81%E4%B8%9A&Id=400783',null)"},{"name":"403954.杭州九洲大药房连锁有限公司仙林苑店 (浙CB5715394)","url":"javascript:commitForECMA(callbackC,'content.jsp?tableId=41&tableName=TABLE41&tableView=%E8%8D%AF%E5%93%81%E7%BB%8F%E8%90%A5%E4%BC%81%E4%B8%9A&Id=400784',null)"},{"name":"403955.杭州九洲大药房连锁有限公司武林路店 (浙CB5717423)","url":"javascript:commitForECMA(callbackC,'content.jsp?tableId=41&tableName=TABLE41&tableView=%E8%8D%AF%E5%93%81%E7%BB%8F%E8%90%A5%E4%BC%81%E4%B8%9A&Id=400785',null)"},{"name":"403956.上海好药师益佑大药房 (沪CA0190176)","url":"javascript:commitForECMA(callbackC,'content.jsp?tableId=41&tableName=TABLE41&tableView=%E8%8D%AF%E5%93%81%E7%BB%8F%E8%90%A5%E4%BC%81%E4%B8%9A&Id=400786',null)"},{"name":"403957.万鑫药房江北区鑫顺药店 (渝CA0060363)","url":"javascript:commitForECMA(callbackC,'content.jsp?tableId=41&tableName=TABLE41&tableView=%E8%8D%AF%E5%93%81%E7%BB%8F%E8%90%A5%E4%BC%81%E4%B8%9A&Id=400787',null)"},{"name":"403958.国药控股菏泽有限公司 (鲁AA5301552)","url":"javascript:commitForECMA(callbackC,'content.jsp?tableId=41&tableName=TABLE41&tableView=%E8%8D%AF%E5%93%81%E7%BB%8F%E8%90%A5%E4%BC%81%E4%B8%9A&Id=400788',null)"},{"name":"403959.长乐市吴航新四季药店 (闽DB591G070)","url":"javascript:commitForECMA(callbackC,'content.jsp?tableId=41&tableName=TABLE41&tableView=%E8%8D%AF%E5%93%81%E7%BB%8F%E8%90%A5%E4%BC%81%E4%B8%9A&Id=400789',null)"},{"name":"403960.长乐松下新祥和药店 (闽DB591G097)","url":"javascript:commitForECMA(callbackC,'content.jsp?tableId=41&tableName=TABLE41&tableView=%E8%8D%AF%E5%93%81%E7%BB%8F%E8%90%A5%E4%BC%81%E4%B8%9A&Id=400790',null)"},{"name":"403961.长乐金峰全民大药房 (闽DB591G098)","url":"javascript:commitForECMA(callbackC,'content.jsp?tableId=41&tableName=TABLE41&tableView=%E8%8D%AF%E5%93%81%E7%BB%8F%E8%90%A5%E4%BC%81%E4%B8%9A&Id=400791',null)"},{"name":"403962.长乐市力康医药商店 (闽DB591G103)","url":"javascript:commitForECMA(callbackC,'content.jsp?tableId=41&tableName=TABLE41&tableView=%E8%8D%AF%E5%93%81%E7%BB%8F%E8%90%A5%E4%BC%81%E4%B8%9A&Id=400792',null)"},{"name":"403963.长乐两港益康堂药店 (闽DB591G100)","url":"javascript:commitForECMA(callbackC,'content.jsp?tableId=41&tableName=TABLE41&tableView=%E8%8D%AF%E5%93%81%E7%BB%8F%E8%90%A5%E4%BC%81%E4%B8%9A&Id=400793',null)"},{"name":"403964.榆林市榆阳区九龙堂大药房东沙店 (陕DB9120672)","url":"javascript:commitForECMA(callbackC,'content.jsp?tableId=41&tableName=TABLE41&tableView=%E8%8D%AF%E5%93%81%E7%BB%8F%E8%90%A5%E4%BC%81%E4%B8%9A&Id=400770',null)"},{"name":"403965.安国福仁大药房 (冀DA3123059)","url":"javascript:commitForECMA(callbackC,'content.jsp?tableId=41&tableName=TABLE41&tableView=%E8%8D%AF%E5%93%81%E7%BB%8F%E8%90%A5%E4%BC%81%E4%B8%9A&Id=401137',null)"}]