[{"name":"405361.山西医科大学第二医院川至药房 (并DA20150029)","url":"javascript:commitForECMA(callbackC,'content.jsp?tableId=41&tableName=TABLE41&tableView=%E8%8D%AF%E5%93%81%E7%BB%8F%E8%90%A5%E4%BC%81%E4%B8%9A&Id=406010',null)"},{"name":"405362.赣州红旗大药房有限公司长塘村分店 (虔(Ⅱ)0579―HQ009)","url":"javascript:commitForECMA(callbackC,'content.jsp?tableId=41&tableName=TABLE41&tableView=%E8%8D%AF%E5%93%81%E7%BB%8F%E8%90%A5%E4%BC%81%E4%B8%9A&Id=406011',null)"},{"name":"405363.赣州华宁康医药零售连锁有限公司杨村药店 (虔(Ⅱ)0636-HNK002)","url":"javascript:commitForECMA(callbackC,'content.jsp?tableId=41&tableName=TABLE41&tableView=%E8%8D%AF%E5%93%81%E7%BB%8F%E8%90%A5%E4%BC%81%E4%B8%9A&Id=406012',null)"},{"name":"405364.兴国中阳大药房零售连锁有限公司华坪店 (虔(Ⅱ)0638―ZY032)","url":"javascript:commitForECMA(callbackC,'content.jsp?tableId=41&tableName=TABLE41&tableView=%E8%8D%AF%E5%93%81%E7%BB%8F%E8%90%A5%E4%BC%81%E4%B8%9A&Id=406013',null)"},{"name":"405365.江西和欣大药房连锁有限公司于都和德瑞药店 (虔(Ⅱ)0639―HX014)","url":"javascript:commitForECMA(callbackC,'content.jsp?tableId=41&tableName=TABLE41&tableView=%E8%8D%AF%E5%93%81%E7%BB%8F%E8%90%A5%E4%BC%81%E4%B8%9A&Id=406014',null)"},{"name":"405366.江西昌盛大药房有限公司于都祥城店 (虔(Ⅱ)0640―CS020)","url":"javascript:commitForECMA(callbackC,'content.jsp?tableId=41&tableName=TABLE41&tableView=%E8%8D%AF%E5%93%81%E7%BB%8F%E8%90%A5%E4%BC%81%E4%B8%9A&Id=406015',null)"},{"name":"405367.江西昌盛大药房有限公司于都东溪新村店 (虔(Ⅱ)0642-CS021)","url":"javascript:commitForECMA(callbackC,'content.jsp?tableId=41&tableName=TABLE41&tableView=%E8%8D%AF%E5%93%81%E7%BB%8F%E8%90%A5%E4%BC%81%E4%B8%9A&Id=406016',null)"},{"name":"405368.江西鸿福大药房连锁有限公司新田店 (虔(Ⅱ)0645-HF018)","url":"javascript:commitForECMA(callbackC,'content.jsp?tableId=41&tableName=TABLE41&tableView=%E8%8D%AF%E5%93%81%E7%BB%8F%E8%90%A5%E4%BC%81%E4%B8%9A&Id=406017',null)"},{"name":"405369.信丰县华仁康大药房零售连锁有限公司同益市场路店 (虔(Ⅱ)0646-HRK001)","url":"javascript:commitForECMA(callbackC,'content.jsp?tableId=41&tableName=TABLE41&tableView=%E8%8D%AF%E5%93%81%E7%BB%8F%E8%90%A5%E4%BC%81%E4%B8%9A&Id=406018',null)"},{"name":"405370.江西和欣大药房连锁有限公司赣县江口店 (虔(Ⅱ)0647-HX016)","url":"javascript:commitForECMA(callbackC,'content.jsp?tableId=41&tableName=TABLE41&tableView=%E8%8D%AF%E5%93%81%E7%BB%8F%E8%90%A5%E4%BC%81%E4%B8%9A&Id=406019',null)"},{"name":"405371.贵阳市白云区同和丰黄氏药房 (黔CA520181055N)","url":"javascript:commitForECMA(callbackC,'content.jsp?tableId=41&tableName=TABLE41&tableView=%E8%8D%AF%E5%93%81%E7%BB%8F%E8%90%A5%E4%BC%81%E4%B8%9A&Id=406020',null)"},{"name":"405372.沙洋县毛李述华药店 (鄂DA7240647)","url":"javascript:commitForECMA(callbackC,'content.jsp?tableId=41&tableName=TABLE41&tableView=%E8%8D%AF%E5%93%81%E7%BB%8F%E8%90%A5%E4%BC%81%E4%B8%9A&Id=406021',null)"},{"name":"405373.赤壁市九德堂大药房 (鄂DA1060360)","url":"javascript:commitForECMA(callbackC,'content.jsp?tableId=41&tableName=TABLE41&tableView=%E8%8D%AF%E5%93%81%E7%BB%8F%E8%90%A5%E4%BC%81%E4%B8%9A&Id=406022',null)"},{"name":"405374.石家庄新世康药房 (冀DA31100077)","url":"javascript:commitForECMA(callbackC,'content.jsp?tableId=41&tableName=TABLE41&tableView=%E8%8D%AF%E5%93%81%E7%BB%8F%E8%90%A5%E4%BC%81%E4%B8%9A&Id=406023',null)"},{"name":"405375.柳河县德济仁堂大药房 (吉DA4350224)","url":"javascript:commitForECMA(callbackC,'content.jsp?tableId=41&tableName=TABLE41&tableView=%E8%8D%AF%E5%93%81%E7%BB%8F%E8%90%A5%E4%BC%81%E4%B8%9A&Id=406024',null)"}]