[{"name":"28321.赣州济民大药房连锁有限公司明德药店 (虔（Ⅲ）1234-JM095)","url":"javascript:commitForECMA(callbackC,'content.jsp?tableId=41&tableName=TABLE41&tableView=%E8%8D%AF%E5%93%81%E7%BB%8F%E8%90%A5%E4%BC%81%E4%B8%9A&Id=27495',null)"},{"name":"28322.赣县友康大药房 (虔（II）2929-GX131)","url":"javascript:commitForECMA(callbackC,'content.jsp?tableId=41&tableName=TABLE41&tableView=%E8%8D%AF%E5%93%81%E7%BB%8F%E8%90%A5%E4%BC%81%E4%B8%9A&Id=27496',null)"},{"name":"28323.赣县百姓缘大药房 (虔（II）2928-GX130)","url":"javascript:commitForECMA(callbackC,'content.jsp?tableId=41&tableName=TABLE41&tableView=%E8%8D%AF%E5%93%81%E7%BB%8F%E8%90%A5%E4%BC%81%E4%B8%9A&Id=27497',null)"},{"name":"28324.信丰县西牛轩康大药房 (虔（II）2924-XF230)","url":"javascript:commitForECMA(callbackC,'content.jsp?tableId=41&tableName=TABLE41&tableView=%E8%8D%AF%E5%93%81%E7%BB%8F%E8%90%A5%E4%BC%81%E4%B8%9A&Id=27498',null)"},{"name":"28325.赣州济民大药房连锁有限公司环城西路药店 (虔（Ⅲ）1216-JM078)","url":"javascript:commitForECMA(callbackC,'content.jsp?tableId=41&tableName=TABLE41&tableView=%E8%8D%AF%E5%93%81%E7%BB%8F%E8%90%A5%E4%BC%81%E4%B8%9A&Id=27499',null)"},{"name":"28326.赣州华尔康大药房零售连锁有限公司 环城路店 (虔（Ⅲ）1193-HEK097)","url":"javascript:commitForECMA(callbackC,'content.jsp?tableId=41&tableName=TABLE41&tableView=%E8%8D%AF%E5%93%81%E7%BB%8F%E8%90%A5%E4%BC%81%E4%B8%9A&Id=27500',null)"},{"name":"28327.赣州华尔康大药房零售连锁有限公司 育英店 (虔（Ⅲ）1192-HEK096)","url":"javascript:commitForECMA(callbackC,'content.jsp?tableId=41&tableName=TABLE41&tableView=%E8%8D%AF%E5%93%81%E7%BB%8F%E8%90%A5%E4%BC%81%E4%B8%9A&Id=27501',null)"},{"name":"28328.赣州华尔康大药房零售连锁有限公司 大余店 (虔（Ⅲ）1191-HEK095)","url":"javascript:commitForECMA(callbackC,'content.jsp?tableId=41&tableName=TABLE41&tableView=%E8%8D%AF%E5%93%81%E7%BB%8F%E8%90%A5%E4%BC%81%E4%B8%9A&Id=27502',null)"},{"name":"28329.于都县铁山垅裕铭国药店 (虔（II）2923-YD220)","url":"javascript:commitForECMA(callbackC,'content.jsp?tableId=41&tableName=TABLE41&tableView=%E8%8D%AF%E5%93%81%E7%BB%8F%E8%90%A5%E4%BC%81%E4%B8%9A&Id=27503',null)"},{"name":"28330.江西太极大药房连锁有限公司赣州厚德店 (虔（Ⅲ）1179-ZTJ034)","url":"javascript:commitForECMA(callbackC,'content.jsp?tableId=41&tableName=TABLE41&tableView=%E8%8D%AF%E5%93%81%E7%BB%8F%E8%90%A5%E4%BC%81%E4%B8%9A&Id=27504',null)"},{"name":"28331.寻乌吉潭吉泰药店第三分店 (虔（Ⅱ）2166-XW086)","url":"javascript:commitForECMA(callbackC,'content.jsp?tableId=41&tableName=TABLE41&tableView=%E8%8D%AF%E5%93%81%E7%BB%8F%E8%90%A5%E4%BC%81%E4%B8%9A&Id=27505',null)"},{"name":"28332.上犹县百姓康大药房 (虔（II）2921-SY104)","url":"javascript:commitForECMA(callbackC,'content.jsp?tableId=41&tableName=TABLE41&tableView=%E8%8D%AF%E5%93%81%E7%BB%8F%E8%90%A5%E4%BC%81%E4%B8%9A&Id=27506',null)"},{"name":"28333.寻乌县吉潭吉泰药店第二分店 (虔（Ⅱ）2164-XW085)","url":"javascript:commitForECMA(callbackC,'content.jsp?tableId=41&tableName=TABLE41&tableView=%E8%8D%AF%E5%93%81%E7%BB%8F%E8%90%A5%E4%BC%81%E4%B8%9A&Id=27507',null)"},{"name":"28334.定南县惠民大药房 (虔（Ⅱ）2160-DN067)","url":"javascript:commitForECMA(callbackC,'content.jsp?tableId=41&tableName=TABLE41&tableView=%E8%8D%AF%E5%93%81%E7%BB%8F%E8%90%A5%E4%BC%81%E4%B8%9A&Id=27508',null)"},{"name":"28335.赣州市八一四晓春大药房 (虔（Ⅱ）2159-ZGQ244)","url":"javascript:commitForECMA(callbackC,'content.jsp?tableId=41&tableName=TABLE41&tableView=%E8%8D%AF%E5%93%81%E7%BB%8F%E8%90%A5%E4%BC%81%E4%B8%9A&Id=27509',null)"}]