[{"name":"38911.湖北智仁大药房有限公司园艺文化街店 (鄂CB2015090802)","url":"javascript:commitForECMA(callbackC,'content.jsp?tableId=41&tableName=TABLE41&tableView=%E8%8D%AF%E5%93%81%E7%BB%8F%E8%90%A5%E4%BC%81%E4%B8%9A&Id=37605',null)"},{"name":"38912.钟祥市永康医药有限公司钟祥药都普济堂店 (鄂07CbⅢ3063)","url":"javascript:commitForECMA(callbackC,'content.jsp?tableId=41&tableName=TABLE41&tableView=%E8%8D%AF%E5%93%81%E7%BB%8F%E8%90%A5%E4%BC%81%E4%B8%9A&Id=37606',null)"},{"name":"38913.向海大药房连锁云梦杏林药店 (鄂06CaⅢ0462)","url":"javascript:commitForECMA(callbackC,'content.jsp?tableId=41&tableName=TABLE41&tableView=%E8%8D%AF%E5%93%81%E7%BB%8F%E8%90%A5%E4%BC%81%E4%B8%9A&Id=37607',null)"},{"name":"38914.向海大药店连锁云梦航航药店 (鄂06CaⅢ0469)","url":"javascript:commitForECMA(callbackC,'content.jsp?tableId=41&tableName=TABLE41&tableView=%E8%8D%AF%E5%93%81%E7%BB%8F%E8%90%A5%E4%BC%81%E4%B8%9A&Id=37608',null)"},{"name":"38915.向海大药房连锁云梦广济药店 (鄂06CaⅢ0461)","url":"javascript:commitForECMA(callbackC,'content.jsp?tableId=41&tableName=TABLE41&tableView=%E8%8D%AF%E5%93%81%E7%BB%8F%E8%90%A5%E4%BC%81%E4%B8%9A&Id=37609',null)"},{"name":"38916.孝感海泰医药连锁有限公司 (鄂BA07120013（更）)","url":"javascript:commitForECMA(callbackC,'content.jsp?tableId=41&tableName=TABLE41&tableView=%E8%8D%AF%E5%93%81%E7%BB%8F%E8%90%A5%E4%BC%81%E4%B8%9A&Id=37610',null)"},{"name":"38917.向海大药房连锁云梦康鑫药店 (鄂06CaⅢ0455)","url":"javascript:commitForECMA(callbackC,'content.jsp?tableId=41&tableName=TABLE41&tableView=%E8%8D%AF%E5%93%81%E7%BB%8F%E8%90%A5%E4%BC%81%E4%B8%9A&Id=37611',null)"},{"name":"38918.赤壁市华顺大药房 (鄂DB0360066)","url":"javascript:commitForECMA(callbackC,'content.jsp?tableId=41&tableName=TABLE41&tableView=%E8%8D%AF%E5%93%81%E7%BB%8F%E8%90%A5%E4%BC%81%E4%B8%9A&Id=37612',null)"},{"name":"38919.十堰市宏康医药商场连锁有限公司武当山特区一分店 (鄂09DaK017)","url":"javascript:commitForECMA(callbackC,'content.jsp?tableId=41&tableName=TABLE41&tableView=%E8%8D%AF%E5%93%81%E7%BB%8F%E8%90%A5%E4%BC%81%E4%B8%9A&Id=37613',null)"},{"name":"38920.荆州同济堂药房有限公司荆州长大药店 (鄂13CbⅢ0174)","url":"javascript:commitForECMA(callbackC,'content.jsp?tableId=41&tableName=TABLE41&tableView=%E8%8D%AF%E5%93%81%E7%BB%8F%E8%90%A5%E4%BC%81%E4%B8%9A&Id=37614',null)"},{"name":"38921.田阳县有源中药材经营部 (桂DB7760021)","url":"javascript:commitForECMA(callbackC,'content.jsp?tableId=41&tableName=TABLE41&tableView=%E8%8D%AF%E5%93%81%E7%BB%8F%E8%90%A5%E4%BC%81%E4%B8%9A&Id=37615',null)"},{"name":"38922.麻城市顺河镇百康药店 (鄂08DaⅢ80035)","url":"javascript:commitForECMA(callbackC,'content.jsp?tableId=41&tableName=TABLE41&tableView=%E8%8D%AF%E5%93%81%E7%BB%8F%E8%90%A5%E4%BC%81%E4%B8%9A&Id=37616',null)"},{"name":"38923.湖北盛世君安连锁有限公司盛世君安大药房江碧路店 (鄂05CbIII0031(A)（更）)","url":"javascript:commitForECMA(callbackC,'content.jsp?tableId=41&tableName=TABLE41&tableView=%E8%8D%AF%E5%93%81%E7%BB%8F%E8%90%A5%E4%BC%81%E4%B8%9A&Id=37617',null)"},{"name":"38924.遂宁市开发区修正堂博特医药连锁祥顺堂店 (川CB8252953)","url":"javascript:commitForECMA(callbackC,'content.jsp?tableId=41&tableName=TABLE41&tableView=%E8%8D%AF%E5%93%81%E7%BB%8F%E8%90%A5%E4%BC%81%E4%B8%9A&Id=37618',null)"},{"name":"38925.随州市曾都区奥康大药房 (鄂10DallZ100)","url":"javascript:commitForECMA(callbackC,'content.jsp?tableId=41&tableName=TABLE41&tableView=%E8%8D%AF%E5%93%81%E7%BB%8F%E8%90%A5%E4%BC%81%E4%B8%9A&Id=37619',null)"}]