[{"name":"61456.永州市益生药品零售连锁零陵区珠山镇火湘桥分店 (湘CB746S305（换）)","url":"javascript:commitForECMA(callbackC,'content.jsp?tableId=41&tableName=TABLE41&tableView=%E8%8D%AF%E5%93%81%E7%BB%8F%E8%90%A5%E4%BC%81%E4%B8%9A&Id=61033',null)"},{"name":"61457.东安县馨惠康大药房 (湘DA7469046（换）)","url":"javascript:commitForECMA(callbackC,'content.jsp?tableId=41&tableName=TABLE41&tableView=%E8%8D%AF%E5%93%81%E7%BB%8F%E8%90%A5%E4%BC%81%E4%B8%9A&Id=61034',null)"},{"name":"61458.河北华佗药房医药连锁有限公司赤城县龙关店 (冀CB31304350)","url":"javascript:commitForECMA(callbackC,'content.jsp?tableId=41&tableName=TABLE41&tableView=%E8%8D%AF%E5%93%81%E7%BB%8F%E8%90%A5%E4%BC%81%E4%B8%9A&Id=61035',null)"},{"name":"61459.长沙市雨花区九华崇缘堂大药房雷田药店 (湘CB7315819)","url":"javascript:commitForECMA(callbackC,'content.jsp?tableId=41&tableName=TABLE41&tableView=%E8%8D%AF%E5%93%81%E7%BB%8F%E8%90%A5%E4%BC%81%E4%B8%9A&Id=61036',null)"},{"name":"61460.重庆鑫斛药房连锁有限公司鑫斛药庄杨公桥店 (渝CB0070977)","url":"javascript:commitForECMA(callbackC,'content.jsp?tableId=41&tableName=TABLE41&tableView=%E8%8D%AF%E5%93%81%E7%BB%8F%E8%90%A5%E4%BC%81%E4%B8%9A&Id=61037',null)"},{"name":"61461.张家口润佳药房医药连锁有限公司怀安康捷店 (冀CB31306082)","url":"javascript:commitForECMA(callbackC,'content.jsp?tableId=41&tableName=TABLE41&tableView=%E8%8D%AF%E5%93%81%E7%BB%8F%E8%90%A5%E4%BC%81%E4%B8%9A&Id=61038',null)"},{"name":"61462.重庆市万和药房连锁有限公司渝北区长安锦绣城店 (渝CB1300940)","url":"javascript:commitForECMA(callbackC,'content.jsp?tableId=41&tableName=TABLE41&tableView=%E8%8D%AF%E5%93%81%E7%BB%8F%E8%90%A5%E4%BC%81%E4%B8%9A&Id=61039',null)"},{"name":"61463.张家口润佳药房医药连锁有限公司怀安渡口堡店 (冀CB31306066)","url":"javascript:commitForECMA(callbackC,'content.jsp?tableId=41&tableName=TABLE41&tableView=%E8%8D%AF%E5%93%81%E7%BB%8F%E8%90%A5%E4%BC%81%E4%B8%9A&Id=61040',null)"},{"name":"61464.廊坊顺康医药零售连锁有限公司霸州十五店 (冀CB0501935)","url":"javascript:commitForECMA(callbackC,'content.jsp?tableId=41&tableName=TABLE41&tableView=%E8%8D%AF%E5%93%81%E7%BB%8F%E8%90%A5%E4%BC%81%E4%B8%9A&Id=61041',null)"},{"name":"61465.贵州仁谊堂医药连锁有限公司仁怀三合店 (黔（仁）CA520382017)","url":"javascript:commitForECMA(callbackC,'content.jsp?tableId=41&tableName=TABLE41&tableView=%E8%8D%AF%E5%93%81%E7%BB%8F%E8%90%A5%E4%BC%81%E4%B8%9A&Id=61042',null)"},{"name":"61466.东安县济民益生大药房 (湘CB7469037（换）)","url":"javascript:commitForECMA(callbackC,'content.jsp?tableId=41&tableName=TABLE41&tableView=%E8%8D%AF%E5%93%81%E7%BB%8F%E8%90%A5%E4%BC%81%E4%B8%9A&Id=61043',null)"},{"name":"61467.佳盛药房重庆市荣昌区峰高街道辉才店 (渝CB0240179)","url":"javascript:commitForECMA(callbackC,'content.jsp?tableId=41&tableName=TABLE41&tableView=%E8%8D%AF%E5%93%81%E7%BB%8F%E8%90%A5%E4%BC%81%E4%B8%9A&Id=61044',null)"},{"name":"61468.长沙市岳麓区白鹤诺舟大药房 (湘CB7315821)","url":"javascript:commitForECMA(callbackC,'content.jsp?tableId=41&tableName=TABLE41&tableView=%E8%8D%AF%E5%93%81%E7%BB%8F%E8%90%A5%E4%BC%81%E4%B8%9A&Id=61045',null)"},{"name":"61469.重庆红瑞乐邦医药有限责任公司 (渝DB0071055)","url":"javascript:commitForECMA(callbackC,'content.jsp?tableId=41&tableName=TABLE41&tableView=%E8%8D%AF%E5%93%81%E7%BB%8F%E8%90%A5%E4%BC%81%E4%B8%9A&Id=61046',null)"},{"name":"61470.廊坊顺康医药零售连锁有限公司霸州十六店 (冀CB0501936)","url":"javascript:commitForECMA(callbackC,'content.jsp?tableId=41&tableName=TABLE41&tableView=%E8%8D%AF%E5%93%81%E7%BB%8F%E8%90%A5%E4%BC%81%E4%B8%9A&Id=61047',null)"}]